ssd/__init__.py
ssd/ssd_rg/__init__.py
ssd/ssd_rg/predict.py
ssd/ssd_rg/train.py
ssd/ssd_rg/ssd_keras/__init__.py
ssd/ssd_rg/ssd_keras/bounding_box_utils/__init__.py
ssd/ssd_rg/ssd_keras/bounding_box_utils/bounding_box_utils.py
ssd/ssd_rg/ssd_keras/data_generator/__init__.py
ssd/ssd_rg/ssd_keras/data_generator/data_augmentation_chain_constant_input_size.py
ssd/ssd_rg/ssd_keras/data_generator/data_augmentation_chain_original_ssd.py
ssd/ssd_rg/ssd_keras/data_generator/data_augmentation_chain_satellite.py
ssd/ssd_rg/ssd_keras/data_generator/data_augmentation_chain_variable_input_size.py
ssd/ssd_rg/ssd_keras/data_generator/object_detection_2d_data_generator.py
ssd/ssd_rg/ssd_keras/data_generator/object_detection_2d_geometric_ops.py
ssd/ssd_rg/ssd_keras/data_generator/object_detection_2d_image_boxes_validation_utils.py
ssd/ssd_rg/ssd_keras/data_generator/object_detection_2d_misc_utils.py
ssd/ssd_rg/ssd_keras/data_generator/object_detection_2d_patch_sampling_ops.py
ssd/ssd_rg/ssd_keras/data_generator/object_detection_2d_photometric_ops.py
ssd/ssd_rg/ssd_keras/eval_utils/__init__.py
ssd/ssd_rg/ssd_keras/eval_utils/average_precision_evaluator.py
ssd/ssd_rg/ssd_keras/eval_utils/coco_utils.py
ssd/ssd_rg/ssd_keras/keras_layers/__init__.py
ssd/ssd_rg/ssd_keras/keras_layers/keras_layer_AnchorBoxes.py
ssd/ssd_rg/ssd_keras/keras_layers/keras_layer_DecodeDetections.py
ssd/ssd_rg/ssd_keras/keras_layers/keras_layer_DecodeDetectionsFast.py
ssd/ssd_rg/ssd_keras/keras_layers/keras_layer_L2Normalization.py
ssd/ssd_rg/ssd_keras/keras_loss_function/__init__.py
ssd/ssd_rg/ssd_keras/keras_loss_function/keras_ssd_loss.py
ssd/ssd_rg/ssd_keras/misc_utils/__init__.py
ssd/ssd_rg/ssd_keras/misc_utils/tensor_sampling_utils.py
ssd/ssd_rg/ssd_keras/models/__init__.py
ssd/ssd_rg/ssd_keras/models/keras_ssd300.py
ssd/ssd_rg/ssd_keras/models/keras_ssd512.py
ssd/ssd_rg/ssd_keras/models/keras_ssd7.py
ssd/ssd_rg/ssd_keras/ssd_encoder_decoder/__init__.py
single_shot_detector-0.2.dist-info/LICENSE
single_shot_detector-0.2.dist-info/METADATA
single_shot_detector-0.2.dist-info/WHEEL
single_shot_detector-0.2.dist-info/top_level.txt
single_shot_detector-0.2.dist-info/RECORD
