Metadata-Version: 2.1
Name: single-shot-detector
Version: 0.2
Summary: Implementação Generica de um single shot detector
Home-page: UNKNOWN
Author: André Bargas
Author-email: andrebargas@gmail.com
License: UNKNOWN
Platform: UNKNOWN
Classifier: Programming Language :: Python :: 3
Classifier: License :: OSI Approved :: MIT License
Classifier: Operating System :: OS Independent
